nose_leak_detector
