Metadata-Version: 1.1
Name: nose-leak-detector
Version: 0.1.5
Summary: A Nose plugin that detects leaks between tests, mainly with mocks
Home-page: https://github.com/Nextdoor/nose-leak-detector
Author: Andrew S. Brown
Author-email: asbrown@nextdoor.com
License: BSD
Download-URL: https://github.com/Nextdoor/nose-leak-detector/archive/0.1.5#egg=nose-leak-detector-0.1.5
Keywords: testing,memory,nose,mocks
Platform: UNKNOWN
Classifier: Development Status :: 4 - Beta
Classifier: Environment :: Console
Classifier: Intended Audience :: Developers
Classifier: Natural Language :: English
Classifier: License :: OSI Approved :: BSD License
Classifier: Operating System :: OS Independent
Classifier: Programming Language :: Python :: 2
Classifier: Programming Language :: Python :: 2.6
Classifier: Programming Language :: Python :: 2.7
Classifier: Programming Language :: Python :: 3
Classifier: Programming Language :: Python :: 3.2
Classifier: Programming Language :: Python :: 3.3
Classifier: Topic :: Software Development :: Testing
